onedash/Adapter.py
onedash/DialogflowAdapter.py
onedash/FacebookAdapter.py
onedash/Rasa.py
onedash/__init__.py
onedash/config.py
onedash/Fields/Intent.py
onedash/Fields/Message.py
onedash/Fields/Record.py
onedash/Fields/Reference.py
onedash/Fields/User.py
onedash/Fields/__init__.py
onedash-0.3.0.dist-info/LICENSE.txt
onedash-0.3.0.dist-info/METADATA
onedash-0.3.0.dist-info/WHEEL
onedash-0.3.0.dist-info/top_level.txt
onedash-0.3.0.dist-info/RECORD
