Metadata-Version: 2.1
Name: onedash
Version: 0.3.0
Summary: OneDash adapter. Helps you to use onedash.cc analytics in your python bot
Home-page: UNKNOWN
Author: EORA OneDash
Author-email: onedash@eora.ru
License: UNKNOWN
Keywords: analytic
Platform: UNKNOWN
Requires-Dist: requests
